avemedi_lib/__init__.py
avemedi_lib/functions.py
avemedi_lib-0.1.6.dist-info/METADATA
avemedi_lib-0.1.6.dist-info/WHEEL
avemedi_lib-0.1.6.dist-info/top_level.txt
avemedi_lib-0.1.6.dist-info/RECORD
