Metadata-Version: 2.1
Name: avemedi-lib
Version: 0.1.6
Summary: This library help in getting a "average value of numbers list" and "get median (for ordered, unordered list of numbers and even or odd list values)". Enjoy.
Author: zelenchyks@gmail.com
License: MIT
Platform: UNKNOWN
Requires-Python: >=3.6
